OctoLingo/__init__.py
OctoLingo/exceptions.py
OctoLingo/file_handler.py
OctoLingo/glossary.py
OctoLingo/history.py
OctoLingo/ocr.py
OctoLingo/translator.py
OctoLingo/utils.py
octolingo-0.3.0.dist-info/licenses/LICENSE
octolingo-0.3.0.dist-info/METADATA
octolingo-0.3.0.dist-info/WHEEL
octolingo-0.3.0.dist-info/top_level.txt
octolingo-0.3.0.dist-info/RECORD
