Metadata-Version: 2.4
Name: OctoLingo
Version: 0.3.0
Summary: A Python package for translating large texts with advanced features including OCR support.
Author: Birhan Tamiru
Author-email: birhantamiru281@gmail.com
Keywords: translation ocr language text-processing
Classifier: Programming Language :: Python :: 3
Classifier: License :: OSI Approved :: MIT License
Classifier: Operating System :: OS Independent
Classifier: Intended Audience :: Developers
Classifier: Intended Audience :: Science/Research
Classifier: Topic :: Text Processing :: Linguistic
Classifier: Topic :: Software Development :: Libraries :: Python Modules
Requires-Python: >=3.7
License-File: LICENSE
Requires-Dist: googletrans==4.0.0-rc1
Requires-Dist: easyocr>=1.6.2
Requires-Dist: python-magic>=0.4.27
Requires-Dist: pillow>=9.5.0
Requires-Dist: pdfplumber>=0.9.0
Requires-Dist: python-docx>=0.8.11
Requires-Dist: asyncio>=3.4.3
Provides-Extra: windows
Requires-Dist: python-magic-bin>=0.4.14; extra == "windows"
Provides-Extra: linux
Requires-Dist: python-magic>=0.4.27; extra == "linux"
Provides-Extra: mac
Requires-Dist: python-magic>=0.4.27; extra == "mac"
Dynamic: author
Dynamic: author-email
Dynamic: classifier
Dynamic: description
Dynamic: description-content-type
Dynamic: keywords
Dynamic: license-file
Dynamic: provides-extra
Dynamic: requires-dist
Dynamic: requires-python
Dynamic: summary
